tap_tableau/__init__.py
tap_tableau/schemas/connections.json
tap_tableau/schemas/datasources.json
tap_tableau/schemas/groups.json
tap_tableau/schemas/projects.json
tap_tableau/schemas/schedules.json
tap_tableau/schemas/tasks.json
tap_tableau/schemas/users.json
tap_tableau/schemas/workbooks.json
tap_tableau/tableau/__init__.py
tap_tableau/tableau/connections.py
tap_tableau/tableau/datasources.py
tap_tableau/tableau/groups.py
tap_tableau/tableau/permissions.py
tap_tableau/tableau/projects.py
tap_tableau/tableau/schedules.py
tap_tableau/tableau/tasks.py
tap_tableau/tableau/users.py
tap_tableau/tableau/utils.py
tap_tableau/tableau/workbooks.py
tap_tableau-0.0.8.dist-info/LICENSE
tap_tableau-0.0.8.dist-info/METADATA
tap_tableau-0.0.8.dist-info/WHEEL
tap_tableau-0.0.8.dist-info/entry_points.txt
tap_tableau-0.0.8.dist-info/top_level.txt
tap_tableau-0.0.8.dist-info/RECORD
