Metadata-Version: 2.1
Name: tap-tableau
Version: 0.0.8
Summary: Singer tap for extracting data from the Tableau API
Home-page: https://github.com/gary-beautypie/tap-tableau
Author: gary.james@beautypie.com
License: UNKNOWN
Platform: UNKNOWN
Classifier: Programming Language :: Python :: 3 :: Only
Requires-Dist: singer-python (>=5.8.0)
Requires-Dist: requests (>=2.20.0)
Requires-Dist: tableauserverclient (>=0.15.0)
Provides-Extra: dev
Requires-Dist: pylint ; extra == 'dev'
Requires-Dist: nose ; extra == 'dev'
